circaPy/__init__.py
circaPy/activity.py
circaPy/episodes.py
circaPy/periodogram.py
circaPy/plots.py
circaPy/preprocessing.py
circaPy/sleep_process.py
circaPy/.idea/actigraphy_analysis.iml
circaPy/.idea/misc.xml
circaPy/.idea/modules.xml
circaPy/.idea/vcs.xml
circaPy/.idea/workspace.xml
circapy-0.1.5.dist-info/METADATA
circapy-0.1.5.dist-info/WHEEL
circapy-0.1.5.dist-info/licenses/LICENSE
circapy-0.1.5.dist-info/RECORD
