Metadata-Version: 2.3
Name: circaPy
Version: 0.1.5
Summary: For analysing circadian activity data
Project-URL: Homepage, https://github.com/A-Fisk/circaPy
Project-URL: Issues, https://github.com/A-Fisk/circaPy/issues
Author-email: Angus Fisk <angus_fisk@hotmail.com>
Keywords: circadian
Classifier: License :: OSI Approved :: GNU General Public License v3 (GPLv3)
Classifier: Operating System :: MacOS
Classifier: Programming Language :: Python :: 3
Requires-Python: >=3.9
